reqchecker/__init__.py
reqchecker/checkers.py
reqchecker/cli.py
reqchecker/reqchecker.py
reqchecker-0.2.1.dist-info/AUTHORS.rst
reqchecker-0.2.1.dist-info/METADATA
reqchecker-0.2.1.dist-info/WHEEL
reqchecker-0.2.1.dist-info/entry_points.txt
reqchecker-0.2.1.dist-info/top_level.txt
reqchecker-0.2.1.dist-info/RECORD
