Metadata-Version: 2.1
Name: reqchecker
Version: 0.2.1
Summary: Compare python package requirements across packages.
Home-page: https://github.com/robertson-mark/reqchecker
Author: Mark Robertson
Author-email: markrobertson@u.boisestate.edu
License: UNKNOWN
Keywords: reqchecker
Platform: UNKNOWN
Classifier: Development Status :: 2 - Pre-Alpha
Classifier: Intended Audience :: Developers
Classifier: Natural Language :: English
Classifier: Programming Language :: Python :: 3.5
Classifier: Programming Language :: Python :: 3.6
Classifier: Programming Language :: Python :: 3.7
Classifier: Programming Language :: Python :: 3.8
Requires-Python: !=3.0.*, !=3.1.*, !=3.2.*, !=3.3.*, !=3.4.*
Requires-Dist: coloredlogs (==6.1)
Requires-Dist: pygithub (==1.44.1)
Requires-Dist: requests (==2.20.1)
